pyrdt/__init__.py
pyrdt/atom.py
pyrdt/combo.py
pyrdt/math.py
pyrdt/stat.py
pywfz/__init__.py
pywfz/atom.py
pywfz/combo.py
pywfz/math.py
pywfz/stat.py
pywfz/wfz_select_data.py
pywfz001/__init__.py
pywfz001/atom.py
pywfz001/combo.py
pywfz001/math.py
pywfz001/stat.py
pywfz001/wfz_select_data.py
pywfz001-1.0.1.dist-info/LICENSE
pywfz001-1.0.1.dist-info/METADATA
pywfz001-1.0.1.dist-info/WHEEL
pywfz001-1.0.1.dist-info/top_level.txt
pywfz001-1.0.1.dist-info/RECORD
