Metadata-Version: 2.1
Name: pywfz001
Version: 1.0.1
Summary: reshape data type in py language 
Home-page: http://www.reshapedata.com
Author: tom
Author-email: hulilei@takewiki.com.cn
License: Apache License
Keywords: reshapedata,rdt,pywfz001
Platform: UNKNOWN
Requires-Python: >=3.6
License-File: LICENSE
Requires-Dist: requests
